week6/q1.v
module q1(d,clk,reset,q);
 input d,clk,reset;
 output reg q;
 always @(posedge clk)
        if (!reset)
            q <= d;
    always @(reset)
        if (reset)
            q <= 0;

endmodule

week6/q1_tb.v


`timescale 1ns/1ns
`include "q1.v"

module q1_tb();
reg d,clk,reset;
wire q;

q1 dFFq(d,clk,reset,q);
always #20 clk = ~clk;
initial
begin
    $dumpfile("q1_tb.vcd");
    $dumpvars(0,q1_tb);
    clk = 0;
    #80 $finish;
end
initial
begin
    d=1; reset=1;#10;
    d=1; reset=0;#20;
    d=1; reset=1;#10;
    d=0; reset=1;#10;
    d=1; reset=0;#20;
    d=0; reset=0;#10;
    $display("Test complete");
end
endmodule

week6/q1_tb.vcd
$date
	Wed Oct  4 14:33:53 2023
$end
$version
	Icarus Verilog
$end
$timescale
	1ns
$end
$scope module q1_tb $end
$var wire 1 ! q $end
$var reg 1 " clk $end
$var reg 1 # d $end
$var reg 1 $ reset $end
$scope module dFFq $end
$var wire 1 " clk $end
$var wire 1 # d $end
$var wire 1 $ reset $end
$var reg 1 ! q $end
$upscope $end
$upscope $end
$enddefinitions $end
#0
$dumpvars
1$
1#
0"
0!
$end
#10
0$
#20
1!
1"
#30
0!
1$
#40
0#
0"
#50
0$
1#
#60
1!
1"
#70
0#
