week6/q3.v
module q3(j,k,clk,reset,q);
    input j,k,clk,reset;
    output reg q;

    always @(posedge clk)
    begin
        if (reset)
            q <= 0;
        else
        begin
            if (clk)
            begin
                if (!q)
                begin
                    if (j)
                        q <= 1;
                end
                else
                begin
                    if (k) 
                        q <= 0;
                end
            end
        end
    end
endmodule

week6/q3_tb.v
`timescale 1ns/1ns
`include "q3.v"

module q3_tb();
reg j,k,clk,reset;
wire q;

q3 jkFFq(j,k,clk,reset,q);
always #10 clk = ~clk;
initial
begin
    $dumpfile("q3_tb.vcd");
    $dumpvars(0,q3_tb);
    clk = 1;
    #120 $finish;
end
initial
begin
    j=0;k=0;reset=1;#10;
    j=0;k=0;reset=0;#20;
    j=1;k=0;reset=0;#20;
    j=0;k=1;reset=0;#20;
    j=1;k=1;reset=0;#20;
    j=0;k=0;reset=1;#20;
    j=0;k=0;reset=0;#10;

end
endmodule

week6/q3_tb.vcd
$date
	Wed Oct  4 15:03:03 2023
$end
$version
	Icarus Verilog
$end
$timescale
	1ns
$end
$scope module q3_tb $end
$var wire 1 ! q $end
$var reg 1 " clk $end
$var reg 1 # j $end
$var reg 1 $ k $end
$var reg 1 % reset $end
$scope module jkFFq $end
$var wire 1 " clk $end
$var wire 1 # j $end
$var wire 1 $ k $end
$var wire 1 % reset $end
$var reg 1 ! q $end
$upscope $end
$upscope $end
$enddefinitions $end
#0
$dumpvars
1%
0$
0#
1"
0!
$end
#10
0%
0"
#20
1"
#30
0"
1#
#40
1!
1"
#50
0"
1$
0#
#60
0!
1"
#70
0"
1#
#80
1!
1"
#90
0"
1%
0$
0#
#100
0!
1"
#110
0"
0%
