week6/q4.v
module q4(Q,S,R,clk,reset);
input S,R,clk,reset;
output reg Q;
always@(negedge clk)
begin
if(reset==1'b0)
Q<=1'b0;
else if(S==0&&R==1)
Q<=1'b0;
else if(S==1&&R==0)
Q<=1'b1;
end
endmodule

week6/q4_tb.v
`timescale 1ns/1ns
`include "q4.v"

module q4_tb();
reg S,R,clk,reset;
wire Q;

q4 u(Q,S,R,clk,reset);
initial
begin
    $dumpfile("q4_tb.vcd");
    $dumpvars(0,q4_tb);
    clk = 1'b1;
    forever#10 clk=~clk;
end
initial
begin
    S=0;R=0;reset=0;#10;
    S=0;R=0;reset=1;#20;
    S=0;R=1;reset=0;#20;
    S=0;R=1;reset=1;#20;
    S=1;R=0;reset=0;#20;
    S=1;R=0;reset=1;#20;
    S=1;R=1;reset=0;#10;
    S=1;R=1;reset=1;#10;
$finish;
end
endmodule

week6/q4_tb.vcd
$date
	Wed Oct  4 15:15:53 2023
$end
$version
	Icarus Verilog
$end
$timescale
	1ns
$end
$scope module q4_tb $end
$var wire 1 ! Q $end
$var reg 1 " R $end
$var reg 1 # S $end
$var reg 1 $ clk $end
$var reg 1 % reset $end
$scope module u $end
$var wire 1 " R $end
$var wire 1 # S $end
$var wire 1 $ clk $end
$var wire 1 % reset $end
$var reg 1 ! Q $end
$upscope $end
$upscope $end
$enddefinitions $end
#0
$dumpvars
0%
1$
0#
0"
x!
$end
#10
1%
0$
#20
1$
#30
0!
0$
0%
1"
#40
1$
#50
0$
1%
#60
1$
#70
0$
0%
0"
1#
#80
1$
#90
1!
0$
1%
#100
1$
#110
0!
0$
0%
1"
#120
1$
1%
