week1/q4.v
module q4(a,b,c,d,e);
input a,c,b,d;
output e;
assign e=((~c|d)&(~a|d)&(a|~b|c|~d));
endmodule

week1/q4_tb.v
`timescale 1ns/1ns
`include "q4.v" //name of the verilog file
module q4_tb ;
reg a,b,c,d;
wire e;
q4 ex(a,b,c,d,e); //installation of the module 
initial 
begin 
$dumpfile("q4_tb.vcd");
$dumpvars(0,q4_tb);
a=1'b0;b=1'b0;c=1'b0;d=1'b0;#20;
a=1'b0;b=1'b0;c=1'b0;d=1'b1;#20;
a=1'b0;b=1'b0;c=1'b1;d=1'b0;#20;
a=1'b0;b=1'b0;c=1'b1;d=1'b1;#20;
a=1'b0;b=1'b1;c=1'b0;d=1'b0;#20;
a=1'b0;b=1'b1;c=1'b0;d=1'b1;#20;
a=1'b0;b=1'b1;c=1'b1;d=1'b0;#20;
a=1'b0;b=1'b1;c=1'b1;d=1'b1;#20;

a=1'b1;b=1'b0;c=1'b0;d=1'b0;#20;
a=1'b1;b=1'b0;c=1'b0;d=1'b1;#20;
a=1'b1;b=1'b0;c=1'b1;d=1'b0;#20;
a=1'b1;b=1'b0;c=1'b1;d=1'b1;#20;
a=1'b1;b=1'b1;c=1'b0;d=1'b0;#20;
a=1'b1;b=1'b1;c=1'b0;d=1'b1;#20;
a=1'b1;b=1'b1;c=1'b1;d=1'b0;#20;
a=1'b1;b=1'b1;c=1'b1;d=1'b1;#20;

$display("test completed");
end 
endmodule

week1/q4_tb.vcd
$date
	Tue Aug  8 21:17:01 2023
$end
$version
	Icarus Verilog
$end
$timescale
	1ns
$end
$scope module q4_tb $end
$var wire 1 ! e $end
$var reg 1 " a $end
$var reg 1 # b $end
$var reg 1 $ c $end
$var reg 1 % d $end
$scope module ex $end
$var wire 1 " a $end
$var wire 1 # b $end
$var wire 1 $ c $end
$var wire 1 % d $end
$var wire 1 ! e $end
$upscope $end
$upscope $end
$enddefinitions $end
#0
$dumpvars
0%
0$
0#
0"
1!
$end
#20
1%
#40
0!
0%
1$
#60
1!
1%
#80
0%
0$
1#
#100
0!
1%
#120
0%
1$
#140
1!
1%
#160
0!
0%
0$
0#
1"
#180
1!
1%
#200
0!
0%
1$
#220
1!
1%
#240
0!
0%
0$
1#
#260
1!
1%
#280
0!
0%
1$
#300
1!
1%
