week10/l10q1.v
module jkff(q,j,k,clk,reset);
input j,k,reset,clk;
output reg q;
always@ (negedge reset or negedge clk)
if (!reset)
	q<=0;
else
	case ({j,k})
		2'b00: q<=q;
		2'b01: q<=0;
		2'b10: q<=1;
		2'b11: q<=~q;
	endcase
endmodule

module l10q1(A,clk,reset);
input clk,reset;
output [2:0]A;
jkff ff1(A[2],A[1],A[1]&A[0],clk,reset);
jkff ff2(A[1],A[0],~A[2]|A[0],clk,reset);
jkff ff3(A[0],A[2]|~A[1],1'b1,clk,reset);
endmodule

week10/l10q1_tb.v
`timescale 1ns/1ns
`include "l10q1.v"
module l10q1_tb;
reg clk,reset;
wire [2:0]A;
l10q1 c00(A,clk,reset);
initial begin
	clk=0;
	forever #10 clk=~clk;
end

initial begin
	$dumpfile("l10q1_tb.vcd");
	$dumpvars(0, l10q1_tb);
	reset=0; #20;
	reset=1; #200;
	$finish;
end
endmodule

week10/l10q1_tb.vcd
$date
	Thu Nov  2 10:05:14 2023
$end
$version
	Icarus Verilog
$end
$timescale
	1ns
$end
$scope module l10q1_tb $end
$var wire 3 ! A [2:0] $end
$var reg 1 " clk $end
$var reg 1 # reset $end
$scope module c00 $end
$var wire 1 " clk $end
$var wire 1 # reset $end
$var wire 3 $ A [2:0] $end
$scope module ff1 $end
$var wire 1 " clk $end
$var wire 1 % j $end
$var wire 1 & k $end
$var wire 1 # reset $end
$var reg 1 ' q $end
$upscope $end
$scope module ff2 $end
$var wire 1 " clk $end
$var wire 1 ( j $end
$var wire 1 ) k $end
$var wire 1 # reset $end
$var reg 1 * q $end
$upscope $end
$scope module ff3 $end
$var wire 1 " clk $end
$var wire 1 + j $end
$var wire 1 , k $end
$var wire 1 # reset $end
$var reg 1 - q $end
$upscope $end
$upscope $end
$upscope $end
$enddefinitions $end
#0
$dumpvars
0-
1,
1+
0*
1)
0(
0'
0&
0%
b0 $
0#
0"
b0 !
$end
#10
1"
#20
1(
b1 !
b1 $
1-
0"
1#
#30
1"
#40
0+
1%
0(
1*
b10 !
b10 $
0-
0"
#50
1"
#60
0)
1+
0%
0*
b100 !
b100 $
1'
0"
#70
1"
#80
1)
1(
b101 !
b101 $
1-
0"
#90
1"
#100
0)
0(
1%
0-
b110 !
b110 $
1*
0"
#110
1"
#120
1)
1&
1(
b111 !
b111 $
1-
0"
#130
1"
#140
0&
1+
0(
0%
0-
0*
b0 !
b0 $
0'
0"
#150
1"
#160
1(
b1 !
b1 $
1-
0"
#170
1"
#180
0+
0(
1%
0-
b10 !
b10 $
1*
0"
#190
1"
#200
0)
1+
0%
1'
b100 !
b100 $
0*
0"
#210
1"
#220
1)
1(
b101 !
b101 $
1-
0"
