Week2/adder.v
module adder(x,y,cin,S,cout);
input s,x,y,cin;
output S,cout;
assign S=x^y^cin;
assign cout=(x&y)|(cin&y)|(x&cin);
endmodule

Week2/adder_tb.v
`timescale 1ns/1ns
`include "adder.v"

module adder_tb;
reg x,y,cin;
wire S,cout;
adder h1(x,y,cin,S,cout);
initial begin
 
 $dumpfile("adder_tb.vcd");
 $dumpvars(0,adder_tb);
 
 x=0;
 y=0;
 cin=0;
 #20;
 
 x=0;
 y=0;
 cin=1;
 #20;
 
 x=0;
 y=1;
 cin=0;
 #20;
 
 x=0;
 y=1;
 cin=1;
 #20;
 
 x=1;
 y=0;
 cin=0;
 #20;
 

 x=1;
 y=0;
 cin=1;
 #20;
 

 x=1;
 y=1;
 cin=0;
 #20;
 
 x=1;
 y=1;
 cin=1;
 #20;
 
 $display("Test complete");
 end
 endmodule

Week2/adder_tb.vcd
$date
	Mon Aug 14 20:12:30 2023
$end
$version
	Icarus Verilog
$end
$timescale
	1ns
$end
$scope module adder_tb $end
$var wire 1 ! cout $end
$var wire 1 " S $end
$var reg 1 # cin $end
$var reg 1 $ x $end
$var reg 1 % y $end
$scope module h1 $end
$var wire 1 " S $end
$var wire 1 # cin $end
$var wire 1 ! cout $end
$var wire 1 & s $end
$var wire 1 $ x $end
$var wire 1 % y $end
$upscope $end
$upscope $end
$enddefinitions $end
#0
$dumpvars
z&
0%
0$
0#
0"
0!
$end
#20
1"
1#
#40
0#
1%
#60
1!
0"
1#
#80
0!
1"
0#
0%
1$
#100
1!
0"
1#
#120
0#
1%
#140
1"
1#
