week2/q1.v
module q1(a,b,c,d,f);
input a,b,c,d;
output f;
assign f=(a&(c^d))|(b&(c^~d));
endmodule

week2/q1_tb.v
`timescale 1ns/1ns
`include "q1.v" //name of the verilog file
module q1_tb;
reg a,b,c,d;
wire f;
q1 ex(a,b,c,d,f); //installation of the module 
initial 
begin 
$dumpfile("q1_tb.vcd");
$dumpvars(0,q1_tb);
a=1'b0;b=1'b0;c=1'b0;d=1'b0;#20;
a=1'b0;b=1'b0;c=1'b0;d=1'b1;#20;
a=1'b0;b=1'b0;c=1'b1;d=1'b0;#20;
a=1'b0;b=1'b0;c=1'b1;d=1'b1;#20;
a=1'b0;b=1'b1;c=1'b0;d=1'b0;#20;
a=1'b0;b=1'b1;c=1'b0;d=1'b1;#20;
a=1'b0;b=1'b1;c=1'b1;d=1'b0;#20;
a=1'b0;b=1'b1;c=1'b1;d=1'b1;#20;
a=1'b1;b=1'b0;c=1'b0;d=1'b0;#20;
a=1'b1;b=1'b0;c=1'b0;d=1'b1;#20;
a=1'b1;b=1'b0;c=1'b1;d=1'b0;#20;
a=1'b1;b=1'b0;c=1'b1;d=1'b1;#20;
a=1'b1;b=1'b1;c=1'b0;d=1'b0;#20;
a=1'b1;b=1'b1;c=1'b0;d=1'b1;#20;
a=1'b1;b=1'b1;c=1'b1;d=1'b0;#20;
a=1'b1;b=1'b1;c=1'b1;d=1'b1;#20;
$display("test completed");
end
endmodule

week2/q1_tb.vcd
$date
	Tue Aug 22 20:30:21 2023
$end
$version
	Icarus Verilog
$end
$timescale
	1ns
$end
$scope module q1_tb $end
$var wire 1 ! f $end
$var reg 1 " a $end
$var reg 1 # b $end
$var reg 1 $ c $end
$var reg 1 % d $end
$scope module ex $end
$var wire 1 " a $end
$var wire 1 # b $end
$var wire 1 $ c $end
$var wire 1 % d $end
$var wire 1 ! f $end
$upscope $end
$upscope $end
$enddefinitions $end
#0
$dumpvars
0%
0$
0#
0"
0!
$end
#20
1%
#40
0%
1$
#60
1%
#80
1!
0%
0$
1#
#100
0!
1%
#120
0%
1$
#140
1!
1%
#160
0!
0%
0$
0#
1"
#180
1!
1%
#200
0%
1$
#220
0!
1%
#240
1!
0%
0$
1#
#260
1%
#280
0%
1$
#300
1%
