week2/q2.v
module q2(a,b,cin,sum,cout);
input a,b,cin;
output sum,cout;
assign sum=a^b^cin;
assign cout=(a&b)|(b&cin)|(cin&a);
endmodule

week2/q2_tb.v
`timescale 1ns/1ns
`include "q2.v" //name of the verilog file
module q2_tb ;
reg a,b,cin;
wire sum,cout;
q2 ex(a,b,cin,sum,cout); //installation of the module 
initial 
begin 
$dumpfile("q2_tb.vcd");
$dumpvars(0,q2_tb);

a=1'b0;b=1'b0;cin=1'b0;#20;
a=1'b0;b=1'b0;cin=1'b1;#20;
a=1'b0;b=1'b1;cin=1'b0;#20;
a=1'b0;b=1'b1;cin=1'b1;#20;
a=1'b1;b=1'b0;cin=1'b0;#20;
a=1'b1;b=1'b0;cin=1'b1;#20;
a=1'b1;b=1'b1;cin=1'b0;#20;
a=1'b1;b=1'b1;cin=1'b1;#20;


$display("test completed");
end 
endmodule

week2/q2_tb.vcd
$date
	Tue Aug 22 20:40:13 2023
$end
$version
	Icarus Verilog
$end
$timescale
	1ns
$end
$scope module q2_tb $end
$var wire 1 ! sum $end
$var wire 1 " cout $end
$var reg 1 # a $end
$var reg 1 $ b $end
$var reg 1 % cin $end
$scope module ex $end
$var wire 1 # a $end
$var wire 1 $ b $end
$var wire 1 % cin $end
$var wire 1 " cout $end
$var wire 1 ! sum $end
$upscope $end
$upscope $end
$enddefinitions $end
#0
$dumpvars
0%
0$
0#
0"
0!
$end
#20
1!
1%
#40
0%
1$
#60
1"
0!
1%
#80
0"
1!
0%
0$
1#
#100
1"
0!
1%
#120
0%
1$
#140
1!
1%
