week4/dec2to4.v
module dec2to4(w,y,en);
input[1:0]w;
input en;
output reg [0:3]y;
always @(w,en)begin
if(en==1)begin
if (w==0)
y=4'b1000;
else if(w==1)
y=4'b0100;
else if(w==2)
y=4'b0010;
else if(w==3)
y=4'b0001;
end 
else begin
y=4'b0000;
end
end
endmodule

week4/dec4to16.v
`include"dec2to4.v"
module dec4to16(w,y,en);
input[3:0]w;
input en;
output[0:15]y;
wire [0:3]m;
dec2to4 st0 (w[3:2],m,en);
dec2to4 st1 (w[1:0],y[0:3],m[0]);
dec2to4 st2 (w[1:0],y[4:7],m[1]);
dec2to4 st3 (w[1:0],y[8:11],m[2]);
dec2to4 st4 (w[1:0],y[12:15],m[3]);
endmodule

week4/dec4to16_tb.v
`timescale 1ns/1ns
`include "dec4to16.v"
module dec4to16_tb;
reg[3:0]w;
reg en;
wire[0:15]y;
dec4to16 uut(w,y,en);
initial begin
$dumpfile("dec4to16_tb.vcd");
$dumpvars(0,dec4to16_tb);
en=1;
w=4'b0000;
#20
en=1;
w=4'b0010;
#20
en=1;
w=4'b0100;
#20
en=1;
w=4'b0110;
#20
en=1;
w=4'b1000;
#20
en=1;
w=4'b1010;
#20
en=1;
w=4'b1100;
#20
en=1;
w=4'b1110;
#20
en=0;
w=4'b1111;
#20
$display("Test complete");
end
endmodule

week4/dec4to16_tb.vcd
$date
	Mon Aug 28 19:51:39 2023
$end
$version
	Icarus Verilog
$end
$timescale
	1ns
$end
$scope module dec4to16_tb $end
$var wire 16 ! y [0:15] $end
$var reg 1 " en $end
$var reg 4 # w [3:0] $end
$scope module uut $end
$var wire 1 " en $end
$var wire 4 $ w [3:0] $end
$var wire 16 % y [0:15] $end
$var wire 4 & m [0:3] $end
$scope module st0 $end
$var wire 1 " en $end
$var wire 2 ' w [1:0] $end
$var reg 4 ( y [0:3] $end
$upscope $end
$scope module st1 $end
$var wire 1 ) en $end
$var wire 2 * w [1:0] $end
$var reg 4 + y [0:3] $end
$upscope $end
$scope module st2 $end
$var wire 1 , en $end
$var wire 2 - w [1:0] $end
$var reg 4 . y [0:3] $end
$upscope $end
$scope module st3 $end
$var wire 1 / en $end
$var wire 2 0 w [1:0] $end
$var reg 4 1 y [0:3] $end
$upscope $end
$scope module st4 $end
$var wire 1 2 en $end
$var wire 2 3 w [1:0] $end
$var reg 4 4 y [0:3] $end
$upscope $end
$upscope $end
$upscope $end
$enddefinitions $end
#0
$dumpvars
b0 4
b0 3
02
b0 1
b0 0
0/
b0 .
b0 -
0,
b1000 +
b0 *
1)
b1000 (
b0 '
b1000 &
b1000000000000000 %
b0 $
b0 #
1"
b1000000000000000 !
$end
#20
b10000000000000 !
b10000000000000 %
b10 +
b10 *
b10 -
b10 0
b10 3
b10 #
b10 $
#40
b1000 .
1,
0)
b100 &
b100 (
b100000000000 !
b100000000000 %
b0 +
b1 '
b0 *
b0 -
b0 0
b0 3
b100 #
b100 $
#60
b1000000000 !
b1000000000 %
b10 .
b10 *
b10 -
b10 0
b10 3
b110 #
b110 $
#80
b1000 1
1/
0,
b10 &
b10 (
b10000000 !
b10000000 %
b0 .
b10 '
b0 *
b0 -
b0 0
b0 3
b1000 #
b1000 $
#100
b100000 !
b100000 %
b10 1
b10 *
b10 -
b10 0
b10 3
b1010 #
b1010 $
#120
b1000 4
12
0/
b1 &
b1 (
b1000 !
b1000 %
b0 1
b11 '
b0 *
b0 -
b0 0
b0 3
b1100 #
b1100 $
#140
b10 !
b10 %
b10 4
b10 *
b10 -
b10 0
b10 3
b1110 #
b1110 $
#160
b0 !
b0 %
b0 4
02
b11 *
b11 -
b11 0
b11 3
b0 &
b0 (
b1111 #
b1111 $
0"
