week3/grtobin.v
module grtobin(G,B);
parameter n=16;
input [n-1:0]G;
output reg [n-1:0]B;
integer i;
always @(G) begin
B[n-1]=G[n-1];
for(i=n-2; i>=0;i=i-1) begin
B[i]=B[i+1]^G[i];
end
end
endmodule

week3/grtobin_tb.v
`timescale 1ns/1ns
`include "grtobin.v"

module grtobin_tb;
parameter n=16;
reg [n-1:0]G;
wire[n-1:0]B;
grtobin vvt(G,B);
initial begin
 
 $dumpfile("grtobin_tb.vcd");
 $dumpvars(0,grtobin_tb);
 
G=1;
#20
 
 G=2;
#20

 G=3;
#20
 
 G=4;
#20

 G=5;
#20

G=6;
#20 
 
 G=7;
#20
 
 G=8;
#20
G=9;
#20
G=10;
#20
G=11;
#20
G=12;
#20
G=13;
#20
G=14;
#20
G=15;
#20


 


 
 $display("Test complete");
 end
 endmodule

week3/grtobin_tb.vcd
$date
	Mon Aug 21 20:19:26 2023
$end
$version
	Icarus Verilog
$end
$timescale
	1ns
$end
$scope module grtobin_tb $end
$var wire 16 ! B [15:0] $end
$var reg 16 " G [15:0] $end
$scope module vvt $end
$var wire 16 # G [15:0] $end
$var reg 16 $ B [15:0] $end
$var integer 32 % i [31:0] $end
$upscope $end
$upscope $end
$enddefinitions $end
#0
$dumpvars
b11111111111111111111111111111111 %
b1 $
b1 #
b1 "
b1 !
$end
#20
b11 !
b11 $
b11111111111111111111111111111111 %
b10 "
b10 #
#40
b10 !
b10 $
b11111111111111111111111111111111 %
b11 "
b11 #
#60
b111 !
b111 $
b11111111111111111111111111111111 %
b100 "
b100 #
#80
b110 !
b110 $
b11111111111111111111111111111111 %
b101 "
b101 #
#100
b100 !
b100 $
b11111111111111111111111111111111 %
b110 "
b110 #
#120
b101 !
b101 $
b11111111111111111111111111111111 %
b111 "
b111 #
#140
b1111 !
b1111 $
b11111111111111111111111111111111 %
b1000 "
b1000 #
#160
b1110 !
b1110 $
b11111111111111111111111111111111 %
b1001 "
b1001 #
#180
b1100 !
b1100 $
b11111111111111111111111111111111 %
b1010 "
b1010 #
#200
b1101 !
b1101 $
b11111111111111111111111111111111 %
b1011 "
b1011 #
#220
b1000 !
b1000 $
b11111111111111111111111111111111 %
b1100 "
b1100 #
#240
b1001 !
b1001 $
b11111111111111111111111111111111 %
b1101 "
b1101 #
#260
b1011 !
b1011 $
b11111111111111111111111111111111 %
b1110 "
b1110 #
#280
b1010 !
b1010 $
b11111111111111111111111111111111 %
b1111 "
b1111 #
