week3/mux4.v
module mux4(s,w,f);
input[1:0]s;
input[3:0]w;
output reg f;
always @(s,w)begin
if(s==0)
f=w[0];
else if(s==1)
f=w[1];
else if(s==2)
f=w[2];
else if(s==3)
f=w[3];
end 
endmodule

week5/mux4_tb.v
`timescale 1ns/1ns
`include "mux4.v"

module mux4_tb;
reg [1:0]s;
reg[3:0]w;
wire f;
mux4 vvt(s,w,f);
initial begin
 
 $dumpfile("mux4_tb.vcd");
 $dumpvars(0,mux4_tb);

s=2'b00; 
w=4'b1110;
#20
 
 s=2'b01; 
 w=4'b0011;
#20
 
 s=2'b10; 
 w=4'b0111;
#20
 
 s=2'b11; 
 w=4'b0100;
#20
 
 s=2'b00; 
 w=4'b0001;
#20
 
 s=2'b01; 
w=4'b0101;
#20
 
 s=2'b10; 
 w=4'b1010;
#20
 
 s=2'b11; 
 w=4'b1001;
#20
 

 
 $display("Test complete");
 end
 endmodule

week3/mux4_tb.vcd
$date
	Mon Aug 21 20:04:28 2023
$end
$version
	Icarus Verilog
$end
$timescale
	1ns
$end
$scope module mux4_tb $end
$var wire 1 ! f $end
$var reg 2 " s [1:0] $end
$var reg 4 # w [3:0] $end
$scope module vvt $end
$var wire 2 $ s [1:0] $end
$var wire 4 % w [3:0] $end
$var reg 1 ! f $end
$upscope $end
$upscope $end
$enddefinitions $end
#0
$dumpvars
b1110 %
b0 $
b1110 #
b0 "
0!
$end
#20
1!
b11 #
b11 %
b1 "
b1 $
#40
b111 #
b111 %
b10 "
b10 $
#60
0!
b100 #
b100 %
b11 "
b11 $
#80
1!
b1 #
b1 %
b0 "
b0 $
#100
0!
b101 #
b101 %
b1 "
b1 $
#120
b1010 #
b1010 %
b10 "
b10 $
#140
1!
b1001 #
b1001 %
b11 "
b11 $
