week3/mux4.v
module mux4(s,w,f);
input[1:0]s;
input[3:0]w;
output reg f;
always @(s,w)begin
if(s==0)
f=w[0];
else if(s==1)
f=w[1];
else if(s==2)
f=w[2];
else if(s==3)
f=w[3];
end 
endmodule

week5/lab5p1.v
`include"mux4.v"
module lab5p1(w,f);
input[1:4]w;
output f;
wire[3:0]m;
assign m[0]=~(w[3]&w[4]) ;
assign m[1]=~ w[4];
assign m[2]=~w[3]&w[4];
assign m[3]=~w[4] ;
mux4 st0 (w[1:2],m,f);
endmodule

week5/lab5p1_tb.v
`timescale 1ns/1ns
`include "lab5p1.v"

module lab5p1_tb;
reg [1:4]w;
wire f;
lab5p1 vvt(w,f);
initial begin
 
 $dumpfile("lab5p1_tb.vcd");
 $dumpvars(0,lab5p1_tb);

//0,1,2,4,6,9,12,14
 w=4'b0000;
#20
w=4'b0001;
#20
w=4'b0010;
#20
w=4'b0100;
#20
w=4'b0110;
#20
 w=4'b1001;
#20
 w=4'b1100;
#20
 w=4'b1110;
#20
  
  
  
 
 

 
 $display("Test complete");
 end
 endmodule

week5/lab5p1_tb.vcd
$date
	Mon Sep  4 19:41:23 2023
$end
$version
	Icarus Verilog
$end
$timescale
	1ns
$end
$scope module lab5p1_tb $end
$var wire 1 ! f $end
$var reg 4 " w [1:4] $end
$scope module vvt $end
$var wire 4 # w [1:4] $end
$var wire 4 $ m [3:0] $end
$var wire 1 ! f $end
$scope module st0 $end
$var wire 2 % s [1:0] $end
$var wire 4 & w [3:0] $end
$var reg 1 ! f $end
$upscope $end
$upscope $end
$upscope $end
$enddefinitions $end
#0
$dumpvars
b1011 &
b0 %
b1011 $
b0 #
b0 "
1!
$end
#20
b101 $
b101 &
b1 "
b1 #
#40
b1011 $
b1011 &
b10 "
b10 #
#60
b1 %
b100 "
b100 #
#80
b110 "
b110 #
#100
b101 $
b101 &
1!
b10 %
b1001 "
b1001 #
#120
b1011 $
b1011 &
1!
b11 %
b1100 "
b1100 #
#140
b1110 "
b1110 #
