week4/dec2to4.v
module dec2to4(w,y,en);
input[1:0]w;
input en;
output reg [0:3]y;
always @(w,en)begin
if(en==1)begin
if (w==0)
y=4'b1000;
else if(w==1)
y=4'b0100;
else if(w==2)
y=4'b0010;
else if(w==3)
y=4'b0001;
end 
else begin
y=4'b0000;
end
end
endmodule

week5/lab5p3.v
`include "dec2to4.v"
module dec4to16(w,y,en);
input[3:0]w;
input en;
output [0:15]y;
wire[0:3]m;
dec2to4 st0 (w[3:2],m,en);
dec2to4 st1 (w[1:0],y[0:3],m[0]);
dec2to4 st2 (w[1:0],y[4:7],m[1]);
dec2to4 st3 (w[1:0],y[8:11],m[2]);
dec2to4 st4 (w[1:0],y[12:15],m[3]);
endmodule
module lab5p3(w,f);
input[3:0]w;
wire[0:15]m;
output f;
dec4to16 st0(w,m,1'b1);
assign f=m[1]|m[4]|m[6]|m[8]|m[9]|m[13]|m[15];
endmodule

week5/lab5p3_tb.v
`timescale 1ns/1ns
`include "lab5p3.v"

module lab5p3_tb;
reg [3:0]w;
wire f;
lab5p3 vvt(w,f);
initial begin
 
 $dumpfile("lab5p3_tb.vcd");
 $dumpvars(0,lab5p3_tb);

w=4'b0000 ;
#20
w=4'b0001 ;
#20
w=4'b0010 ;
#20
w=4'b0011 ;
#20
w=4'b0100 ;
#20
w=4'b0101 ;
#20
w=4'b0110;
#20
w=4'b0111 ;
#20
w=4'b1000 ;
#20
w=4'b1001 ;
#20
w=4'b1010 ;
#20
w=4'b1011 ;
#20
w=4'b1100 ;
#20
w=4'b1101 ;
#20
w=4'b1110;
#20
w=4'b1111 ;
#20
 

 
 $display("Test complete");
 end
 endmodule

week5/lab5p3_tb.vcd
$date
	Mon Sep  4 20:44:11 2023
$end
$version
	Icarus Verilog
$end
$timescale
	1ns
$end
$scope module lab5p3_tb $end
$var wire 1 ! f $end
$var reg 4 " w [3:0] $end
$scope module vvt $end
$var wire 1 ! f $end
$var wire 4 # w [3:0] $end
$var wire 16 $ m [0:15] $end
$scope module st0 $end
$var wire 1 % en $end
$var wire 4 & w [3:0] $end
$var wire 16 ' y [0:15] $end
$var wire 4 ( m [0:3] $end
$scope module st0 $end
$var wire 1 % en $end
$var wire 2 ) w [1:0] $end
$var reg 4 * y [0:3] $end
$upscope $end
$scope module st1 $end
$var wire 1 + en $end
$var wire 2 , w [1:0] $end
$var reg 4 - y [0:3] $end
$upscope $end
$scope module st2 $end
$var wire 1 . en $end
$var wire 2 / w [1:0] $end
$var reg 4 0 y [0:3] $end
$upscope $end
$scope module st3 $end
$var wire 1 1 en $end
$var wire 2 2 w [1:0] $end
$var reg 4 3 y [0:3] $end
$upscope $end
$scope module st4 $end
$var wire 1 4 en $end
$var wire 2 5 w [1:0] $end
$var reg 4 6 y [0:3] $end
$upscope $end
$upscope $end
$upscope $end
$upscope $end
$enddefinitions $end
#0
$dumpvars
b0 6
b0 5
04
b0 3
b0 2
01
b0 0
b0 /
0.
b1000 -
b0 ,
1+
b1000 *
b0 )
b1000 (
b1000000000000000 '
b0 &
1%
b1000000000000000 $
b0 #
b0 "
0!
$end
#20
1!
b100000000000000 $
b100000000000000 '
b100 -
b1 ,
b1 /
b1 2
b1 5
b1 "
b1 #
b1 &
#40
0!
b10000000000000 $
b10000000000000 '
b10 -
b10 ,
b10 /
b10 2
b10 5
b10 "
b10 #
b10 &
#60
b1000000000000 $
b1000000000000 '
b1 -
b11 ,
b11 /
b11 2
b11 5
b11 "
b11 #
b11 &
#80
1!
b1000 0
1.
0+
b100 (
b100 *
b100000000000 $
b100000000000 '
b0 -
b1 )
b0 ,
b0 /
b0 2
b0 5
b100 "
b100 #
b100 &
#100
0!
b10000000000 $
b10000000000 '
b100 0
b1 ,
b1 /
b1 2
b1 5
b101 "
b101 #
b101 &
#120
1!
b1000000000 $
b1000000000 '
b10 0
b10 ,
b10 /
b10 2
b10 5
b110 "
b110 #
b110 &
#140
0!
b100000000 $
b100000000 '
b1 0
b11 ,
b11 /
b11 2
b11 5
b111 "
b111 #
b111 &
#160
1!
b1000 3
11
0.
b10 (
b10 *
b10000000 $
b10000000 '
b0 0
b10 )
b0 ,
b0 /
b0 2
b0 5
b1000 "
b1000 #
b1000 &
#180
b1000000 $
b1000000 '
b100 3
b1 ,
b1 /
b1 2
b1 5
b1001 "
b1001 #
b1001 &
#200
0!
b100000 $
b100000 '
b10 3
b10 ,
b10 /
b10 2
b10 5
b1010 "
b1010 #
b1010 &
#220
b10000 $
b10000 '
b1 3
b11 ,
b11 /
b11 2
b11 5
b1011 "
b1011 #
b1011 &
#240
0!
b1000 6
14
01
b1 (
b1 *
b1000 $
b1000 '
b0 3
b11 )
b0 ,
b0 /
b0 2
b0 5
b1100 "
b1100 #
b1100 &
#260
1!
b100 $
b100 '
b100 6
b1 ,
b1 /
b1 2
b1 5
b1101 "
b1101 #
b1101 &
#280
0!
b10 $
b10 '
b10 6
b10 ,
b10 /
b10 2
b10 5
b1110 "
b1110 #
b1110 &
#300
1!
b1 $
b1 '
b1 6
b11 ,
b11 /
b11 2
b11 5
b1111 "
b1111 #
b1111 &
