week4/dec2to4.v
module dec2to4(w,y,en);
input[1:0]w;
input en;
output reg [0:3]y;
always @(w,en)begin
if(en==1)begin
if (w==0)
y=4'b1000;
else if(w==1)
y=4'b0100;
else if(w==2)
y=4'b0010;
else if(w==3)
y=4'b0001;
end 
else begin
y=4'b0000;
end
end
endmodule

week5/lab5p4.v
`include "dec2to4.v"
module lab5p4(w,f);
input[2:0]w;
output f;
wire[0:7]m;
dec2to4 st0 (w[1:0],m[0:3],~w[2]);
dec2to4 st1 (w[1:0],m[4:7],w[2]);
assign f=m[3]|m[5]|m[6]|m[7];
endmodule

week5/lab5p4_tb.v
`timescale 1ns/1ns
`include "lab5p4.v"

module lab5p4_tb;
reg [2:0]w;
wire f;
lab5p4 vvt(w,f);
initial begin
 
 $dumpfile("lab5p4_tb.vcd");
 $dumpvars(0,lab5p4_tb);

w=3'b000 ;#20
w=3'b001 ;#20
w=3'b010 ;#20
w=3'b011 ;#20
w=3'b100 ;#20
w=3'b101 ;#20
w=3'b110 ;#20
w=3'b111 ;#20
 

 
 $display("Test complete");
 end
 endmodule

week5/lab5p4_tb.vcd
$date
	Mon Sep  4 20:53:54 2023
$end
$version
	Icarus Verilog
$end
$timescale
	1ns
$end
$scope module lab5p4_tb $end
$var wire 1 ! f $end
$var reg 3 " w [2:0] $end
$scope module vvt $end
$var wire 1 ! f $end
$var wire 3 # w [2:0] $end
$var wire 8 $ m [0:7] $end
$scope module st0 $end
$var wire 1 % en $end
$var wire 2 & w [1:0] $end
$var reg 4 ' y [0:3] $end
$upscope $end
$scope module st1 $end
$var wire 1 ( en $end
$var wire 2 ) w [1:0] $end
$var reg 4 * y [0:3] $end
$upscope $end
$upscope $end
$upscope $end
$enddefinitions $end
#0
$dumpvars
b0 *
b0 )
0(
b1000 '
b0 &
1%
b10000000 $
b0 #
b0 "
0!
$end
#20
b1000000 $
b100 '
b1 &
b1 )
b1 "
b1 #
#40
b100000 $
b10 '
b10 &
b10 )
b10 "
b10 #
#60
1!
b10000 $
b1 '
b11 &
b11 )
b11 "
b11 #
#80
0!
b0 '
0%
b1000 $
b1000 *
b0 &
b0 )
1(
b100 "
b100 #
#100
1!
b100 $
b100 *
b1 &
b1 )
b101 "
b101 #
#120
b10 $
b10 *
b10 &
b10 )
b110 "
b110 #
#140
b1 $
b1 *
b11 &
b11 )
b111 "
b111 #
